lab02/RTL/FIR_63TAP.sv
`timescale 1ns/1ps

module FIR_63TAP(
    input logic signed [9:0] in,
    input logic signed [9:0] filt_constants[62:0],
    output logic signed [9:0] out,
    input logic CLK,
    input logic RSTN,
    input logic EN,
    input logic COEFF_EN
);

    logic signed [25:0] intermed[63:0];
    logic signed [19:0] mult[63:0];
    logic signed [9:0] big_reg[62:0];
    logic signed [9:0] filt_consts[62:0];

    // Main sequential block
    always_ff @(posedge CLK, negedge RSTN) begin  
        if (!RSTN) begin
            for (int d = 0; d < 63; d = d + 1) begin
                big_reg[d] <= 0;
                filt_consts[d] <= 0;
            end
            out[9:0] <= 0;
        end 
        else begin
            if (EN) begin
                // Shift register
                for (int d = 1; d < 63; d = d + 1) begin
                    big_reg[d] <= big_reg[d-1];
                end
                big_reg[0] <= in;
            
                // Output scaling - shift right by 8 bits via [16:8] to
                //                  eliminate accumulated 2**8 from using Q1.8
                out[9:0] <= {intermed[63][25], intermed[63][16:8]};
            end
            if (COEFF_EN) begin
                // Load coefficients
                for (int d = 0; d < 63; d = d + 1) begin
                    filt_consts[d] <= filt_constants[d];
                end
            end
        end 
    end

    // Combinational systolic chain
    assign intermed[0] = 26'd0;  // Initialize first accumulator
    
    genvar t;
    generate for (t = 0; t < 63; t = t + 1) begin: dsp01
        assign mult[t] = big_reg[62-t] * filt_consts[t];
        assign intermed[t+1] = mult[t] + intermed[t];
    end
    endgenerate

endmodule

lab02/RTL/tb.sv
`timescale 1ns/1ps

module tb;
    string file_path = "";
    
    logic signed [9:0] filt_constants [62:0];
    logic signed [9:0] in;
    logic rst = 0;
    logic sample_clk = 0;
    logic signed [9:0] out;
    logic en = 0;
    logic coeff_en = 0;  // New coefficient enable signal

    FIR_63TAP DUT (
        .in(in),
        .filt_constants(filt_constants),
        .out(out),
        .CLK(sample_clk),
        .RSTN(rst),
        .EN(en),
        .COEFF_EN(coeff_en)  // Connect new port
    );

    integer fp;
    integer fp2;
    integer status;
    integer rewind_status;
    integer i;

    logic [19:0] en_seq = 20'b11010001000010100010; // New for lab02

    initial begin
        $dumpfile({file_path, "dump.vcd"}); 
        $dumpvars(0, tb);

        // Initialize signals
        in = 10'd0;
        for (i = 0; i < 63; i++) begin
            filt_constants[i] = 10'd0;
        end

        // Reset sequence
        rst = 0;
        en = 0;
        coeff_en = 0;
        #10;
        rst = 1;
        #10;
        
        // Load filter coefficients from file (before enabling)
        fp = $fopen({file_path, "RTL_filter_taps.csv"}, "r");
        if (fp == 0) begin
            $display("Error: Could not open RTL_filter_taps.csv");
            $finish;
        end

        for (i = 0; i < 63; i++) begin
            status = $fscanf(fp, "%d", filt_constants[i]); 
            if (status != 1) begin
                $display("Error: Failed to read coefficient %0d", i);
                $finish;
            end
        end
        $fclose(fp);

        // Enable and load coefficients using coeff_en
        en = 1;
        coeff_en = 1;  // Enable coefficient loading
        
        // Run a few cycles to load coefficients
        repeat(2) begin
            #5;
            sample_clk = 1;
            #5;
            sample_clk = 0;
        end
        
        coeff_en = 0;  // Disable coefficient loading after they're loaded
        
        // Continue running cycles to initialize pipeline with zeros
        for (i = 0; i < 128; i++) begin
            #5;
            sample_clk = 1;
            #5;
            sample_clk = 0;
        end

        // Open input and output files
        fp = $fopen({file_path, "RTL_s400_500_input_signal_shorter.csv"}, "r");
        if (fp == 0) begin
            $display("Error: Could not open RTL_s400_500_input_signal_shorter.csv");
            $finish;
        end
        
        fp2 = $fopen({file_path, "RTL_output.csv"}, "w");
        if (fp2 == 0) begin
            $display("Error: Could not open RTL_output.csv");
            $finish;
        end

        // Added en_seq (see above)
        // - loop for all en_seq bits, for each sample count (or just 20?)
        for (int i = 0; i < 20; i=i+1) begin
            en = en_seq[i]; // toggle EN via en_seq as specified by lab02 instructions
            
            // Rewind input file to beginning for each enable value
            $rewind(fp);
            
            // Process input data into FIR Filter- the output will be delayed by 63 cycles
            // - If using RTL_s400_500_input_signal.csv, there are 160 samples
            // - The combined sinusoid period is 20 cycles
            // - RTL_s400_500_input_signal_shorter.csv is 20 samples
            while (!$feof(fp)) begin
                status = $fscanf(fp, "%d", in); 
                if (status == 1) begin
                    #5;
                    sample_clk = 1;
                    #5;
                    sample_clk = 0;
                    $fdisplay(fp2, "%d", out);
                end
            end
        end

        // Flush pipeline with zeros to get remaining outputs
        in = 10'd0;
        for (i = 0; i < 63; i++) begin
            #5;
            sample_clk = 1;
            #5;
            sample_clk = 0;
            $fdisplay(fp2, "%d", out);
        end

        $fclose(fp);
        $fclose(fp2);
        
        #50 $finish;
    end

endmodule

lab02/dump.vcd
$date
	Wed Jun  3 16:16:38 2026
$end
$version
	Icarus Verilog
$end
$timescale
	1ps
$end
$scope module tb $end
$var wire 10 ! out [9:0] $end
$var reg 1 " coeff_en $end
$var reg 1 # en $end
$var reg 20 $ en_seq [19:0] $end
$var reg 10 % in [9:0] $end
$var reg 1 & rst $end
$var reg 1 ' sample_clk $end
$var integer 32 ( fp [31:0] $end
$var integer 32 ) fp2 [31:0] $end
$var integer 32 * i [31:0] $end
$var integer 32 + status [31:0] $end
$scope module DUT $end
$var wire 1 ' CLK $end
$var wire 1 " COEFF_EN $end
$var wire 1 # EN $end
$var wire 1 & RSTN $end
$var wire 10 , in [9:0] $end
$var reg 10 - out [9:0] $end
$scope begin dsp01[0] $end
$var parameter 2 . t $end
$upscope $end
$scope begin dsp01[1] $end
$var parameter 2 / t $end
$upscope $end
$scope begin dsp01[2] $end
$var parameter 3 0 t $end
$upscope $end
$scope begin dsp01[3] $end
$var parameter 3 1 t $end
$upscope $end
$scope begin dsp01[4] $end
$var parameter 4 2 t $end
$upscope $end
$scope begin dsp01[5] $end
$var parameter 4 3 t $end
$upscope $end
$scope begin dsp01[6] $end
$var parameter 4 4 t $end
$upscope $end
$scope begin dsp01[7] $end
$var parameter 4 5 t $end
$upscope $end
$scope begin dsp01[8] $end
$var parameter 5 6 t $end
$upscope $end
$scope begin dsp01[9] $end
$var parameter 5 7 t $end
$upscope $end
$scope begin dsp01[10] $end
$var parameter 5 8 t $end
$upscope $end
$scope begin dsp01[11] $end
$var parameter 5 9 t $end
$upscope $end
$scope begin dsp01[12] $end
$var parameter 5 : t $end
$upscope $end
$scope begin dsp01[13] $end
$var parameter 5 ; t $end
$upscope $end
$scope begin dsp01[14] $end
$var parameter 5 < t $end
$upscope $end
$scope begin dsp01[15] $end
$var parameter 5 = t $end
$upscope $end
$scope begin dsp01[16] $end
$var parameter 6 > t $end
$upscope $end
$scope begin dsp01[17] $end
$var parameter 6 ? t $end
$upscope $end
$scope begin dsp01[18] $end
$var parameter 6 @ t $end
$upscope $end
$scope begin dsp01[19] $end
$var parameter 6 A t $end
$upscope $end
$scope begin dsp01[20] $end
$var parameter 6 B t $end
$upscope $end
$scope begin dsp01[21] $end
$var parameter 6 C t $end
$upscope $end
$scope begin dsp01[22] $end
$var parameter 6 D t $end
$upscope $end
$scope begin dsp01[23] $end
$var parameter 6 E t $end
$upscope $end
$scope begin dsp01[24] $end
$var parameter 6 F t $end
$upscope $end
$scope begin dsp01[25] $end
$var parameter 6 G t $end
$upscope $end
$scope begin dsp01[26] $end
$var parameter 6 H t $end
$upscope $end
$scope begin dsp01[27] $end
$var parameter 6 I t $end
$upscope $end
$scope begin dsp01[28] $end
$var parameter 6 J t $end
$upscope $end
$scope begin dsp01[29] $end
$var parameter 6 K t $end
$upscope $end
$scope begin dsp01[30] $end
$var parameter 6 L t $end
$upscope $end
$scope begin dsp01[31] $end
$var parameter 6 M t $end
$upscope $end
$scope begin dsp01[32] $end
$var parameter 7 N t $end
$upscope $end
$scope begin dsp01[33] $end
$var parameter 7 O t $end
$upscope $end
$scope begin dsp01[34] $end
$var parameter 7 P t $end
$upscope $end
$scope begin dsp01[35] $end
$var parameter 7 Q t $end
$upscope $end
$scope begin dsp01[36] $end
$var parameter 7 R t $end
$upscope $end
$scope begin dsp01[37] $end
$var parameter 7 S t $end
$upscope $end
$scope begin dsp01[38] $end
$var parameter 7 T t $end
$upscope $end
$scope begin dsp01[39] $end
$var parameter 7 U t $end
$upscope $end
$scope begin dsp01[40] $end
$var parameter 7 V t $end
$upscope $end
$scope begin dsp01[41] $end
$var parameter 7 W t $end
$upscope $end
$scope begin dsp01[42] $end
$var parameter 7 X t $end
$upscope $end
$scope begin dsp01[43] $end
$var parameter 7 Y t $end
$upscope $end
$scope begin dsp01[44] $end
$var parameter 7 Z t $end
$upscope $end
$scope begin dsp01[45] $end
$var parameter 7 [ t $end
$upscope $end
$scope begin dsp01[46] $end
$var parameter 7 \ t $end
$upscope $end
$scope begin dsp01[47] $end
$var parameter 7 ] t $end
$upscope $end
$scope begin dsp01[48] $end
$var parameter 7 ^ t $end
$upscope $end
$scope begin dsp01[49] $end
$var parameter 7 _ t $end
$upscope $end
$scope begin dsp01[50] $end
$var parameter 7 ` t $end
$upscope $end
$scope begin dsp01[51] $end
$var parameter 7 a t $end
$upscope $end
$scope begin dsp01[52] $end
$var parameter 7 b t $end
$upscope $end
$scope begin dsp01[53] $end
$var parameter 7 c t $end
$upscope $end
$scope begin dsp01[54] $end
$var parameter 7 d t $end
$upscope $end
$scope begin dsp01[55] $end
$var parameter 7 e t $end
$upscope $end
$scope begin dsp01[56] $end
$var parameter 7 f t $end
$upscope $end
$scope begin dsp01[57] $end
$var parameter 7 g t $end
$upscope $end
$scope begin dsp01[58] $end
$var parameter 7 h t $end
$upscope $end
$scope begin dsp01[59] $end
$var parameter 7 i t $end
$upscope $end
$scope begin dsp01[60] $end
$var parameter 7 j t $end
$upscope $end
$scope begin dsp01[61] $end
$var parameter 7 k t $end
$upscope $end
$scope begin dsp01[62] $end
$var parameter 7 l t $end
$upscope $end
$scope begin $ivl_for_loop0 $end
$var integer 32 m d [31:0] $end
$upscope $end
$scope begin $ivl_for_loop1 $end
$var integer 32 n d [31:0] $end
$upscope $end
$scope begin $ivl_for_loop2 $end
$var integer 32 o d [31:0] $end
$upscope $end
$upscope $end
$scope begin $ivl_for_loop3 $end
$var integer 32 p i [31:0] $end
$upscope $end
$upscope $end
$enddefinitions $end
$comment Show the parameter values. $end
$dumpall
b111110 l
b111101 k
b111100 j
b111011 i
b111010 h
b111001 g
b111000 f
b110111 e
b110110 d
b110101 c
b110100 b
b110011 a
b110010 `
b110001 _
b110000 ^
b101111 ]
b101110 \
b101101 [
b101100 Z
b101011 Y
b101010 X
b101001 W
b101000 V
b100111 U
b100110 T
b100101 S
b100100 R
b100011 Q
b100010 P
b100001 O
b100000 N
b11111 M
b11110 L
b11101 K
b11100 J
b11011 I
b11010 H
b11001 G
b11000 F
b10111 E
b10110 D
b10101 C
b10100 B
b10011 A
b10010 @
b10001 ?
b10000 >
b1111 =
b1110 <
b1101 ;
b1100 :
b1011 9
b1010 8
b1001 7
b1000 6
b111 5
b110 4
b101 3
b100 2
b11 1
b10 0
b1 /
b0 .
$end
#0
$dumpvars
b0 p
b0 o
b0 n
b0 m
bx -
b0 ,
bx +
b111111 *
bx )
bx (
0'
0&
b0 %
b11010001000010100010 $
0#
0"
bx !
$end
#10000
1&
#20000
1"
1#
b1 +
b111111 *
b10000000000000000000000000000011 (
#25000
b111111 o
b111111 n
1'
#30000
0'
#35000
b111111 o
b111111 n
1'
#40000
b0 *
0"
0'
#45000
b111111 n
1'
#50000
b1 *
0'
#55000
b111111 n
1'
#60000
b10 *
0'
#65000
b111111 n
1'
#70000
b11 *
0'
#75000
b111111 n
1'
#80000
b100 *
0'
#85000
b111111 n
1'
#90000
b101 *
0'
#95000
b111111 n
1'
#100000
b110 *
0'
#105000
b111111 n
1'
#110000
b111 *
0'
#115000
b111111 n
1'
#120000
b1000 *
0'
#125000
b111111 n
1'
#130000
b1001 *
0'
#135000
b111111 n
1'
#140000
b1010 *
0'
#145000
b111111 n
1'
#150000
b1011 *
0'
#155000
b111111 n
1'
#160000
b1100 *
0'
#165000
b111111 n
1'
#170000
b1101 *
0'
#175000
b111111 n
1'
#180000
b1110 *
0'
#185000
b111111 n
1'
#190000
b1111 *
0'
#195000
b111111 n
1'
#200000
b10000 *
0'
#205000
b111111 n
1'
#210000
b10001 *
0'
#215000
b111111 n
1'
#220000
b10010 *
0'
#225000
b111111 n
1'
#230000
b10011 *
0'
#235000
b111111 n
1'
#240000
b10100 *
0'
#245000
b111111 n
1'
#250000
b10101 *
0'
#255000
b111111 n
1'
#260000
b10110 *
0'
#265000
b111111 n
1'
#270000
b10111 *
0'
#275000
b111111 n
1'
#280000
b11000 *
0'
#285000
b111111 n
1'
#290000
b11001 *
0'
#295000
b111111 n
1'
#300000
b11010 *
0'
#305000
b111111 n
1'
#310000
b11011 *
0'
#315000
b111111 n
1'
#320000
b11100 *
0'
#325000
b111111 n
1'
#330000
b11101 *
0'
#335000
b111111 n
1'
#340000
b11110 *
0'
#345000
b111111 n
1'
#350000
b11111 *
0'
#355000
b111111 n
1'
#360000
b100000 *
0'
#365000
b111111 n
1'
#370000
b100001 *
0'
#375000
b111111 n
1'
#380000
b100010 *
0'
#385000
b111111 n
1'
#390000
b100011 *
0'
#395000
b111111 n
1'
#400000
b100100 *
0'
#405000
b111111 n
1'
#410000
b100101 *
0'
#415000
b111111 n
1'
#420000
b100110 *
0'
#425000
b111111 n
1'
#430000
b100111 *
0'
#435000
b111111 n
1'
#440000
b101000 *
0'
#445000
b111111 n
1'
#450000
b101001 *
0'
#455000
b111111 n
1'
#460000
b101010 *
0'
#465000
b111111 n
1'
#470000
b101011 *
0'
#475000
b111111 n
1'
#480000
b101100 *
0'
#485000
b111111 n
1'
#490000
b101101 *
0'
#495000
b111111 n
1'
#500000
b101110 *
0'
#505000
b111111 n
1'
#510000
b101111 *
0'
#515000
b111111 n
1'
#520000
b110000 *
0'
#525000
b111111 n
1'
#530000
b110001 *
0'
#535000
b111111 n
1'
#540000
b110010 *
0'
#545000
b111111 n
1'
#550000
b110011 *
0'
#555000
b111111 n
1'
#560000
b110100 *
0'
#565000
b111111 n
1'
#570000
b110101 *
0'
#575000
b111111 n
1'
#580000
b110110 *
0'
#585000
b111111 n
1'
#590000
b110111 *
0'
#595000
b111111 n
1'
#600000
b111000 *
0'
#605000
b111111 n
1'
#610000
b111001 *
0'
#615000
b111111 n
1'
#620000
b111010 *
0'
#625000
b111111 n
1'
#630000
b111011 *
0'
#635000
b111111 n
1'
#640000
b111100 *
0'
#645000
b111111 n
1'
#650000
b111101 *
0'
#655000
b0 !
b0 -
b111111 n
1'
#660000
b111110 *
0'
#665000
b111111 n
1'
#670000
b111111 *
0'
#675000
b111111 n
1'
#680000
b1000000 *
0'
#685000
b111111 n
1'
#690000
b1000001 *
0'
#695000
b111111 n
1'
#700000
b1000010 *
0'
#705000
b111111 n
1'
#710000
b1000011 *
0'
#715000
b111111 n
1'
#720000
b1000100 *
0'
#725000
b111111 n
1'
#730000
b1000101 *
0'
#735000
b111111 n
1'
#740000
b1000110 *
0'
#745000
b111111 n
1'
#750000
b1000111 *
0'
#755000
b111111 n
1'
#760000
b1001000 *
0'
#765000
b111111 n
1'
#770000
b1001001 *
0'
#775000
b111111 n
1'
#780000
b1001010 *
0'
#785000
b111111 n
1'
#790000
b1001011 *
0'
#795000
b111111 n
1'
#800000
b1001100 *
0'
#805000
b111111 n
1'
#810000
b1001101 *
0'
#815000
b111111 n
1'
#820000
b1001110 *
0'
#825000
b111111 n
1'
#830000
b1001111 *
0'
#835000
b111111 n
1'
#840000
b1010000 *
0'
#845000
b111111 n
1'
#850000
b1010001 *
0'
#855000
b111111 n
1'
#860000
b1010010 *
0'
#865000
b111111 n
1'
#870000
b1010011 *
0'
#875000
b111111 n
1'
#880000
b1010100 *
0'
#885000
b111111 n
1'
#890000
b1010101 *
0'
#895000
b111111 n
1'
#900000
b1010110 *
0'
#905000
b111111 n
1'
#910000
b1010111 *
0'
#915000
b111111 n
1'
#920000
b1011000 *
0'
#925000
b111111 n
1'
#930000
b1011001 *
0'
#935000
b111111 n
1'
#940000
b1011010 *
0'
#945000
b111111 n
1'
#950000
b1011011 *
0'
#955000
b111111 n
1'
#960000
b1011100 *
0'
#965000
b111111 n
1'
#970000
b1011101 *
0'
#975000
b111111 n
1'
#980000
b1011110 *
0'
#985000
b111111 n
1'
#990000
b1011111 *
0'
#995000
b111111 n
1'
#1000000
b1100000 *
0'
#1005000
b111111 n
1'
#1010000
b1100001 *
0'
#1015000
b111111 n
1'
#1020000
b1100010 *
0'
#1025000
b111111 n
1'
#1030000
b1100011 *
0'
#1035000
b111111 n
1'
#1040000
b1100100 *
0'
#1045000
b111111 n
1'
#1050000
b1100101 *
0'
#1055000
b111111 n
1'
#1060000
b1100110 *
0'
#1065000
b111111 n
1'
#1070000
b1100111 *
0'
#1075000
b111111 n
1'
#1080000
b1101000 *
0'
#1085000
b111111 n
1'
#1090000
b1101001 *
0'
#1095000
b111111 n
1'
#1100000
b1101010 *
0'
#1105000
b111111 n
1'
#1110000
b1101011 *
0'
#1115000
b111111 n
1'
#1120000
b1101100 *
0'
#1125000
b111111 n
1'
#1130000
b1101101 *
0'
#1135000
b111111 n
1'
#1140000
b1101110 *
0'
#1145000
b111111 n
1'
#1150000
b1101111 *
0'
#1155000
b111111 n
1'
#1160000
b1110000 *
0'
#1165000
b111111 n
1'
#1170000
b1110001 *
0'
#1175000
b111111 n
1'
#1180000
b1110010 *
0'
#1185000
b111111 n
1'
#1190000
b1110011 *
0'
#1195000
b111111 n
1'
#1200000
b1110100 *
0'
#1205000
b111111 n
1'
#1210000
b1110101 *
0'
#1215000
b111111 n
1'
#1220000
b1110110 *
0'
#1225000
b111111 n
1'
#1230000
b1110111 *
0'
#1235000
b111111 n
1'
#1240000
b1111000 *
0'
#1245000
b111111 n
1'
#1250000
b1111001 *
0'
#1255000
b111111 n
1'
#1260000
b1111010 *
0'
#1265000
b111111 n
1'
#1270000
b1111011 *
0'
#1275000
b111111 n
1'
#1280000
b1111100 *
0'
#1285000
b111111 n
1'
#1290000
b1111101 *
0'
#1295000
b111111 n
1'
#1300000
b1111110 *
0'
#1305000
b111111 n
1'
#1310000
b1111111 *
0'
#1315000
b111111 n
1'
#1320000
0#
b10000000000000000000000000000100 )
b10000000 *
0'
#1325000
1'
#1330000
b111110011 %
b111110011 ,
0'
#1335000
1'
#1340000
b10010110 %
b10010110 ,
0'
#1345000
1'
#1350000
b1001101010 %
b1001101010 ,
0'
#1355000
1'
#1360000
b1100001101 %
b1100001101 ,
0'
#1365000
1'
#1370000
b100000000 %
b100000000 ,
0'
#1375000
1'
#1380000
b11110011 %
b11110011 ,
0'
#1385000
1'
#1390000
b1110010110 %
b1110010110 ,
0'
#1395000
1'
#1400000
b1101101010 %
b1101101010 ,
0'
#1405000
1'
#1410000
b1101 %
b1101 ,
0'
#1415000
1'
#1420000
b0 %
b0 ,
0'
#1425000
1'
#1430000
b1111110011 %
b1111110011 ,
0'
#1435000
1'
#1440000
b10010110 %
b10010110 ,
0'
#1445000
1'
#1450000
b1101010 %
b1101010 ,
0'
#1455000
1'
#1460000
b1100001101 %
b1100001101 ,
0'
#1465000
1'
#1470000
b1100000000 %
b1100000000 ,
0'
#1475000
1'
#1480000
b11110011 %
b11110011 ,
0'
#1485000
1'
#1490000
b110010110 %
b110010110 ,
0'
#1495000
1'
#1500000
b1101101010 %
b1101101010 ,
0'
#1505000
1'
#1510000
b1000001101 %
b1000001101 ,
0'
#1515000
1'
#1520000
b0 %
b0 ,
1#
b1 p
b1 +
0'
#1525000
b111111 n
1'
#1530000
b111110011 %
b111110011 ,
0'
#1535000
b111111 n
1'
#1540000
b10010110 %
b10010110 ,
0'
#1545000
b111111 n
1'
#1550000
b1001101010 %
b1001101010 ,
0'
#1555000
b1111111110 !
b1111111110 -
b111111 n
1'
#1560000
b1100001101 %
b1100001101 ,
0'
#1565000
b1111111101 !
b1111111101 -
b111111 n
1'
#1570000
b100000000 %
b100000000 ,
0'
#1575000
b111111 n
1'
#1580000
b11110011 %
b11110011 ,
0'
#1585000
b111111 n
1'
#1590000
b1110010110 %
b1110010110 ,
0'
#1595000
b1 !
b1 -
b111111 n
1'
#1600000
b1101101010 %
b1101101010 ,
0'
#1605000
b101 !
b101 -
b111111 n
1'
#1610000
b1101 %
b1101 ,
0'
#1615000
b1 !
b1 -
b111111 n
1'
#1620000
b0 %
b0 ,
0'
#1625000
b1111111010 !
b1111111010 -
b111111 n
1'
#1630000
b1111110011 %
b1111110011 ,
0'
#1635000
b1111111000 !
b1111111000 -
b111111 n
1'
#1640000
b10010110 %
b10010110 ,
0'
#1645000
b10 !
b10 -
b111111 n
1'
#1650000
b1101010 %
b1101010 ,
0'
#1655000
b1011 !
b1011 -
b111111 n
1'
#1660000
b1100001101 %
b1100001101 ,
0'
#1665000
b11 !
b11 -
b111111 n
1'
#1670000
b1100000000 %
b1100000000 ,
0'
#1675000
b1111110100 !
b1111110100 -
b111111 n
1'
#1680000
b11110011 %
b11110011 ,
0'
#1685000
b111111 n
1'
#1690000
b110010110 %
b110010110 ,
0'
#1695000
b110 !
b110 -
b111111 n
1'
#1700000
b1101101010 %
b1101101010 ,
0'
#1705000
b10010 !
b10010 -
b111111 n
1'
#1710000
b1000001101 %
b1000001101 ,
0'
#1715000
b10 !
b10 -
b111111 n
1'
#1720000
b0 %
b0 ,
0#
b10 p
b1 +
0'
#1725000
1'
#1730000
b111110011 %
b111110011 ,
0'
#1735000
1'
#1740000
b10010110 %
b10010110 ,
0'
#1745000
1'
#1750000
b1001101010 %
b1001101010 ,
0'
#1755000
1'
#1760000
b1100001101 %
b1100001101 ,
0'
#1765000
1'
#1770000
b100000000 %
b100000000 ,
0'
#1775000
1'
#1780000
b11110011 %
b11110011 ,
0'
#1785000
1'
#1790000
b1110010110 %
b1110010110 ,
0'
#1795000
1'
#1800000
b1101101010 %
b1101101010 ,
0'
#1805000
1'
#1810000
b1101 %
b1101 ,
0'
#1815000
1'
#1820000
b0 %
b0 ,
0'
#1825000
1'
#1830000
b1111110011 %
b1111110011 ,
0'
#1835000
1'
#1840000
b10010110 %
b10010110 ,
0'
#1845000
1'
#1850000
b1101010 %
b1101010 ,
0'
#1855000
1'
#1860000
b1100001101 %
b1100001101 ,
0'
#1865000
1'
#1870000
b1100000000 %
b1100000000 ,
0'
#1875000
1'
#1880000
b11110011 %
b11110011 ,
0'
#1885000
1'
#1890000
b110010110 %
b110010110 ,
0'
#1895000
1'
#1900000
b1101101010 %
b1101101010 ,
0'
#1905000
1'
#1910000
b1000001101 %
b1000001101 ,
0'
#1915000
1'
#1920000
b0 %
b0 ,
b11 p
b1 +
0'
#1925000
1'
#1930000
b111110011 %
b111110011 ,
0'
#1935000
1'
#1940000
b10010110 %
b10010110 ,
0'
#1945000
1'
#1950000
b1001101010 %
b1001101010 ,
0'
#1955000
1'
#1960000
b1100001101 %
b1100001101 ,
0'
#1965000
1'
#1970000
b100000000 %
b100000000 ,
0'
#1975000
1'
#1980000
b11110011 %
b11110011 ,
0'
#1985000
1'
#1990000
b1110010110 %
b1110010110 ,
0'
#1995000
1'
#2000000
b1101101010 %
b1101101010 ,
0'
#2005000
1'
#2010000
b1101 %
b1101 ,
0'
#2015000
1'
#2020000
b0 %
b0 ,
0'
#2025000
1'
#2030000
b1111110011 %
b1111110011 ,
0'
#2035000
1'
#2040000
b10010110 %
b10010110 ,
0'
#2045000
1'
#2050000
b1101010 %
b1101010 ,
0'
#2055000
1'
#2060000
b1100001101 %
b1100001101 ,
0'
#2065000
1'
#2070000
b1100000000 %
b1100000000 ,
0'
#2075000
1'
#2080000
b11110011 %
b11110011 ,
0'
#2085000
1'
#2090000
b110010110 %
b110010110 ,
0'
#2095000
1'
#2100000
b1101101010 %
b1101101010 ,
0'
#2105000
1'
#2110000
b1000001101 %
b1000001101 ,
0'
#2115000
1'
#2120000
b0 %
b0 ,
b100 p
b1 +
0'
#2125000
1'
#2130000
b111110011 %
b111110011 ,
0'
#2135000
1'
#2140000
b10010110 %
b10010110 ,
0'
#2145000
1'
#2150000
b1001101010 %
b1001101010 ,
0'
#2155000
1'
#2160000
b1100001101 %
b1100001101 ,
0'
#2165000
1'
#2170000
b100000000 %
b100000000 ,
0'
#2175000
1'
#2180000
b11110011 %
b11110011 ,
0'
#2185000
1'
#2190000
b1110010110 %
b1110010110 ,
0'
#2195000
1'
#2200000
b1101101010 %
b1101101010 ,
0'
#2205000
1'
#2210000
b1101 %
b1101 ,
0'
#2215000
1'
#2220000
b0 %
b0 ,
0'
#2225000
1'
#2230000
b1111110011 %
b1111110011 ,
0'
#2235000
1'
#2240000
b10010110 %
b10010110 ,
0'
#2245000
1'
#2250000
b1101010 %
b1101010 ,
0'
#2255000
1'
#2260000
b1100001101 %
b1100001101 ,
0'
#2265000
1'
#2270000
b1100000000 %
b1100000000 ,
0'
#2275000
1'
#2280000
b11110011 %
b11110011 ,
0'
#2285000
1'
#2290000
b110010110 %
b110010110 ,
0'
#2295000
1'
#2300000
b1101101010 %
b1101101010 ,
0'
#2305000
1'
#2310000
b1000001101 %
b1000001101 ,
0'
#2315000
1'
#2320000
b0 %
b0 ,
1#
b101 p
b1 +
0'
#2325000
b1111101001 !
b1111101001 -
b111111 n
1'
#2330000
b111110011 %
b111110011 ,
0'
#2335000
b1111110001 !
b1111110001 -
b111111 n
1'
#2340000
b10010110 %
b10010110 ,
0'
#2345000
b10011 !
b10011 -
b111111 n
1'
#2350000
b1001101010 %
b1001101010 ,
0'
#2355000
b11100 !
b11100 -
b111111 n
1'
#2360000
b1100001101 %
b1100001101 ,
0'
#2365000
b1111110111 !
b1111110111 -
b111111 n
1'
#2370000
b100000000 %
b100000000 ,
0'
#2375000
b1111010111 !
b1111010111 -
b111111 n
1'
#2380000
b11110011 %
b11110011 ,
0'
#2385000
b1111110101 !
b1111110101 -
b111111 n
1'
#2390000
b1110010110 %
b1110010110 ,
0'
#2395000
b101110 !
b101110 -
b111111 n
1'
#2400000
b1101101010 %
b1101101010 ,
0'
#2405000
b101000 !
b101000 -
b111111 n
1'
#2410000
b1101 %
b1101 ,
0'
#2415000
b1111010011 !
b1111010011 -
b111111 n
1'
#2420000
b0 %
b0 ,
0'
#2425000
b1110101001 !
b1110101001 -
b111111 n
1'
#2430000
b1111110011 %
b1111110011 ,
0'
#2435000
b11110 !
b11110 -
b111111 n
1'
#2440000
b10010110 %
b10010110 ,
0'
#2445000
b11100010 !
b11100010 -
b111111 n
1'
#2450000
b1101010 %
b1101010 ,
0'
#2455000
b100001100 !
b100001100 -
b111111 n
1'
#2460000
b1100001101 %
b1100001101 ,
0'
#2465000
b111001 !
b111001 -
b111111 n
1'
#2470000
b1100000000 %
b1100000000 ,
0'
#2475000
b1100111111 !
b1100111111 -
b111111 n
1'
#2480000
b11110011 %
b11110011 ,
0'
#2485000
b111111 n
1'
#2490000
b110010110 %
b110010110 ,
0'
#2495000
b110010 !
b110010 -
b111111 n
1'
#2500000
b1101101010 %
b1101101010 ,
0'
#2505000
b11011110 !
b11011110 -
b111111 n
1'
#2510000
b1000001101 %
b1000001101 ,
0'
#2515000
b1100011 !
b1100011 -
b111111 n
1'
#2520000
b0 %
b0 ,
0#
b110 p
b1 +
0'
#2525000
1'
#2530000
b111110011 %
b111110011 ,
0'
#2535000
1'
#2540000
b10010110 %
b10010110 ,
0'
#2545000
1'
#2550000
b1001101010 %
b1001101010 ,
0'
#2555000
1'
#2560000
b1100001101 %
b1100001101 ,
0'
#2565000
1'
#2570000
b100000000 %
b100000000 ,
0'
#2575000
1'
#2580000
b11110011 %
b11110011 ,
0'
#2585000
1'
#2590000
b1110010110 %
b1110010110 ,
0'
#2595000
1'
#2600000
b1101101010 %
b1101101010 ,
0'
#2605000
1'
#2610000
b1101 %
b1101 ,
0'
#2615000
1'
#2620000
b0 %
b0 ,
0'
#2625000
1'
#2630000
b1111110011 %
b1111110011 ,
0'
#2635000
1'
#2640000
b10010110 %
b10010110 ,
0'
#2645000
1'
#2650000
b1101010 %
b1101010 ,
0'
#2655000
1'
#2660000
b1100001101 %
b1100001101 ,
0'
#2665000
1'
#2670000
b1100000000 %
b1100000000 ,
0'
#2675000
1'
#2680000
b11110011 %
b11110011 ,
0'
#2685000
1'
#2690000
b110010110 %
b110010110 ,
0'
#2695000
1'
#2700000
b1101101010 %
b1101101010 ,
0'
#2705000
1'
#2710000
b1000001101 %
b1000001101 ,
0'
#2715000
1'
#2720000
b0 %
b0 ,
1#
b111 p
b1 +
0'
#2725000
b1101100111 !
b1101100111 -
b111111 n
1'
#2730000
b111110011 %
b111110011 ,
0'
#2735000
b1100110111 !
b1100110111 -
b111111 n
1'
#2740000
b10010110 %
b10010110 ,
0'
#2745000
b10011 !
b10011 -
b111111 n
1'
#2750000
b1001101010 %
b1001101010 ,
0'
#2755000
b11010110 !
b11010110 -
b111111 n
1'
#2760000
b1100001101 %
b1100001101 ,
0'
#2765000
b1111001 !
b1111001 -
b111111 n
1'
#2770000
b100000000 %
b100000000 ,
0'
#2775000
b1101110110 !
b1101110110 -
b111111 n
1'
#2780000
b11110011 %
b11110011 ,
0'
#2785000
b1100101001 !
b1100101001 -
b111111 n
1'
#2790000
b1110010110 %
b1110010110 ,
0'
#2795000
b10 !
b10 -
b111111 n
1'
#2800000
b1101101010 %
b1101101010 ,
0'
#2805000
b11011101 !
b11011101 -
b111111 n
1'
#2810000
b1101 %
b1101 ,
0'
#2815000
b10001000 !
b10001000 -
b111111 n
1'
#2820000
b0 %
b0 ,
0'
#2825000
b1101110011 !
b1101110011 -
b111111 n
1'
#2830000
b1111110011 %
b1111110011 ,
0'
#2835000
b1100011110 !
b1100011110 -
b111111 n
1'
#2840000
b10010110 %
b10010110 ,
0'
#2845000
b10 !
b10 -
b111111 n
1'
#2850000
b1101010 %
b1101010 ,
0'
