lab01/RTL/FIR_63TAP.sv
`timescale 1ns/1ps

module FIR_63TAP(
    input logic signed [9:0] in,
    input logic signed [9:0] filt_constant,
    output logic signed [9:0] out,
    input logic CLK,
    input logic RSTN,
    input logic EN,
    input logic FILT_SHIFT
);

    // intermediate variables
    logic signed [25:0] intermed [63:0];
    logic signed [19:0] mult [63:0];
    logic signed [9:0] filt_consts [63:0];
    logic signed [9:0] in2;

    always_ff @(posedge CLK, negedge RSTN) begin  
        if (!RSTN) begin
            filt_consts[0] <= 10'd0;
            intermed[0] <= 26'd0;
            out[9:0] <= 10'd0;
            in2 <= 10'd0;
        end else if (EN) begin
            intermed[0] <= 26'd0;
            filt_consts[0] <= filt_constant;
            in2 <= in;
            out[9:0] <= 10'($signed(intermed[63]) >>> 9);
        end
    end

    genvar i;
    generate for (i = 0; i < 63; i = i + 1) begin : dsp02
        always_comb begin
            mult[i] = 20'(filt_consts[i]) * 20'(in2);
        end
        
        always_ff @(posedge CLK, negedge RSTN) begin  
            if (!RSTN) begin
                intermed[i+1] <= 26'd0;
                filt_consts[i+1] <= 10'd0;
            end else if (EN) begin
                intermed[i+1] <= intermed[i] + mult[i];
                if (FILT_SHIFT) begin
                    filt_consts[i+1] <= filt_consts[i];
                end
            end
        end
    end
    endgenerate

endmodule

lab01/RTL/tb.sv
`timescale 1ns/1ps

string file_path = "";
module tb;
    logic signed [9:0] filt_constant;
    logic signed [9:0] in;
    logic rst = 0;
    logic sample_clk = 0;
    logic signed [9:0] out;
    logic en = 1;
    logic filter_en = 1;

    FIR_63TAP DUT (
        .in(in),
        .filt_constant(filt_constant),
        .out(out),
        .CLK(sample_clk),
        .RSTN(rst),
        .EN(en),
        .FILT_SHIFT(filter_en)
    );

    integer fp;
    integer fp2;
    integer status;

    initial begin
        $dumpfile({file_path, "dump.vcd"}); 
        $dumpvars(0, tb);

        // Reset sequence
        rst = 0;
        #1;
        sample_clk = ~sample_clk;
        #1;
        sample_clk = ~sample_clk;
        #1;
        rst = 1;
        #1;
        en = 1;
        filter_en = 1;

        // Load filter coefficients
        fp = $fopen({file_path, "RTL/filter_taps.txt"}, "r");
        if (fp == 0) begin
            $display("Error: Could not open filter_taps.txt");
            $finish;
        end

        for (int p = 0; p < 63; p = p + 1) begin
            status = $fscanf(fp, "%d", filt_constant); 
            sample_clk = ~sample_clk;
            #1;
            sample_clk = ~sample_clk;
            #1;
        end
        
        $fclose(fp);

        // Process input data
        fp = $fopen({file_path, "RTL/s400_500_input_signal.csv"}, "r");
        if (fp == 0) begin
            $display("Error: Could not open combined.csv");
            $finish;
        end
        
        fp2 = $fopen({file_path, "output.csv"}, "w");
        if (fp2 == 0) begin
            $display("Error: Could not open output.csv");
            $finish;
        end

        en = 1;
        filter_en = 0;

        while (!$feof(fp)) begin
            status = $fscanf(fp, "%d", in); 
            if (status == 1) begin
                sample_clk = ~sample_clk;
                #1;
                sample_clk = ~sample_clk;
                #1;
                $fdisplay(fp2, "%d", out);
            end
        end

        $fclose(fp);
        $fclose(fp2);
        
        #50 $finish;
    end

endmodule

lab01/dump.vcd
$date
	Fri May 22 14:17:41 2026
$end
$version
	Icarus Verilog
$end
$timescale
	1ps
$end
$scope module tb $end
$var wire 10 ! out [9:0] $end
$var reg 1 " en $end
$var reg 10 # filt_constant [9:0] $end
$var reg 1 $ filter_en $end
$var reg 10 % in [9:0] $end
$var reg 1 & rst $end
$var reg 1 ' sample_clk $end
$var integer 32 ( fp [31:0] $end
$var integer 32 ) fp2 [31:0] $end
$var integer 32 * status [31:0] $end
$scope module DUT $end
$var wire 1 ' CLK $end
$var wire 1 " EN $end
$var wire 1 $ FILT_SHIFT $end
$var wire 1 & RSTN $end
$var wire 10 + filt_constant [9:0] $end
$var wire 10 , in [9:0] $end
$var reg 10 - in2 [9:0] $end
$var reg 10 . out [9:0] $end
$scope begin dsp02[0] $end
$var parameter 2 / i $end
$upscope $end
$scope begin dsp02[1] $end
$var parameter 2 0 i $end
$upscope $end
$scope begin dsp02[2] $end
$var parameter 3 1 i $end
$upscope $end
$scope begin dsp02[3] $end
$var parameter 3 2 i $end
$upscope $end
$scope begin dsp02[4] $end
$var parameter 4 3 i $end
$upscope $end
$scope begin dsp02[5] $end
$var parameter 4 4 i $end
$upscope $end
$scope begin dsp02[6] $end
$var parameter 4 5 i $end
$upscope $end
$scope begin dsp02[7] $end
$var parameter 4 6 i $end
$upscope $end
$scope begin dsp02[8] $end
$var parameter 5 7 i $end
$upscope $end
$scope begin dsp02[9] $end
$var parameter 5 8 i $end
$upscope $end
$scope begin dsp02[10] $end
$var parameter 5 9 i $end
$upscope $end
$scope begin dsp02[11] $end
$var parameter 5 : i $end
$upscope $end
$scope begin dsp02[12] $end
$var parameter 5 ; i $end
$upscope $end
$scope begin dsp02[13] $end
$var parameter 5 < i $end
$upscope $end
$scope begin dsp02[14] $end
$var parameter 5 = i $end
$upscope $end
$scope begin dsp02[15] $end
$var parameter 5 > i $end
$upscope $end
$scope begin dsp02[16] $end
$var parameter 6 ? i $end
$upscope $end
$scope begin dsp02[17] $end
$var parameter 6 @ i $end
$upscope $end
$scope begin dsp02[18] $end
$var parameter 6 A i $end
$upscope $end
$scope begin dsp02[19] $end
$var parameter 6 B i $end
$upscope $end
$scope begin dsp02[20] $end
$var parameter 6 C i $end
$upscope $end
$scope begin dsp02[21] $end
$var parameter 6 D i $end
$upscope $end
$scope begin dsp02[22] $end
$var parameter 6 E i $end
$upscope $end
$scope begin dsp02[23] $end
$var parameter 6 F i $end
$upscope $end
$scope begin dsp02[24] $end
$var parameter 6 G i $end
$upscope $end
$scope begin dsp02[25] $end
$var parameter 6 H i $end
$upscope $end
$scope begin dsp02[26] $end
$var parameter 6 I i $end
$upscope $end
$scope begin dsp02[27] $end
$var parameter 6 J i $end
$upscope $end
$scope begin dsp02[28] $end
$var parameter 6 K i $end
$upscope $end
$scope begin dsp02[29] $end
$var parameter 6 L i $end
$upscope $end
$scope begin dsp02[30] $end
$var parameter 6 M i $end
$upscope $end
$scope begin dsp02[31] $end
$var parameter 6 N i $end
$upscope $end
$scope begin dsp02[32] $end
$var parameter 7 O i $end
$upscope $end
$scope begin dsp02[33] $end
$var parameter 7 P i $end
$upscope $end
$scope begin dsp02[34] $end
$var parameter 7 Q i $end
$upscope $end
$scope begin dsp02[35] $end
$var parameter 7 R i $end
$upscope $end
$scope begin dsp02[36] $end
$var parameter 7 S i $end
$upscope $end
$scope begin dsp02[37] $end
$var parameter 7 T i $end
$upscope $end
$scope begin dsp02[38] $end
$var parameter 7 U i $end
$upscope $end
$scope begin dsp02[39] $end
$var parameter 7 V i $end
$upscope $end
$scope begin dsp02[40] $end
$var parameter 7 W i $end
$upscope $end
$scope begin dsp02[41] $end
$var parameter 7 X i $end
$upscope $end
$scope begin dsp02[42] $end
$var parameter 7 Y i $end
$upscope $end
$scope begin dsp02[43] $end
$var parameter 7 Z i $end
$upscope $end
$scope begin dsp02[44] $end
$var parameter 7 [ i $end
$upscope $end
$scope begin dsp02[45] $end
$var parameter 7 \ i $end
$upscope $end
$scope begin dsp02[46] $end
$var parameter 7 ] i $end
$upscope $end
$scope begin dsp02[47] $end
$var parameter 7 ^ i $end
$upscope $end
$scope begin dsp02[48] $end
$var parameter 7 _ i $end
$upscope $end
$scope begin dsp02[49] $end
$var parameter 7 ` i $end
$upscope $end
$scope begin dsp02[50] $end
$var parameter 7 a i $end
$upscope $end
$scope begin dsp02[51] $end
$var parameter 7 b i $end
$upscope $end
$scope begin dsp02[52] $end
$var parameter 7 c i $end
$upscope $end
$scope begin dsp02[53] $end
$var parameter 7 d i $end
$upscope $end
$scope begin dsp02[54] $end
$var parameter 7 e i $end
$upscope $end
$scope begin dsp02[55] $end
$var parameter 7 f i $end
$upscope $end
$scope begin dsp02[56] $end
$var parameter 7 g i $end
$upscope $end
$scope begin dsp02[57] $end
$var parameter 7 h i $end
$upscope $end
$scope begin dsp02[58] $end
$var parameter 7 i i $end
$upscope $end
$scope begin dsp02[59] $end
$var parameter 7 j i $end
$upscope $end
$scope begin dsp02[60] $end
$var parameter 7 k i $end
$upscope $end
$scope begin dsp02[61] $end
$var parameter 7 l i $end
$upscope $end
$scope begin dsp02[62] $end
$var parameter 7 m i $end
$upscope $end
$upscope $end
$scope begin $ivl_for_loop0 $end
$var integer 32 n p [31:0] $end
$upscope $end
$upscope $end
$enddefinitions $end
$comment Show the parameter values. $end
$dumpall
b111110 m
b111101 l
b111100 k
b111011 j
b111010 i
b111001 h
b111000 g
b110111 f
b110110 e
b110101 d
b110100 c
b110011 b
b110010 a
b110001 `
b110000 _
b101111 ^
b101110 ]
b101101 \
b101100 [
b101011 Z
b101010 Y
b101001 X
b101000 W
b100111 V
b100110 U
b100101 T
b100100 S
b100011 R
b100010 Q
b100001 P
b100000 O
b11111 N
b11110 M
b11101 L
b11100 K
b11011 J
b11010 I
b11001 H
b11000 G
b10111 F
b10110 E
b10101 D
b10100 C
b10011 B
b10010 A
b10001 @
b10000 ?
b1111 >
b1110 =
b1101 <
b1100 ;
b1011 :
b1010 9
b1001 8
b1000 7
b111 6
b110 5
b101 4
b100 3
b11 2
b10 1
b1 0
b0 /
$end
#0
$dumpvars
b0 n
bx .
bx -
bx ,
bx +
bx *
bx )
bx (
0'
0&
bx %
1$
bx #
1"
bx !
$end
#1000
b0 -
b0 !
b0 .
1'
#2000
0'
#3000
1&
#4000
bx -
1'
b1 *
b0 #
b0 +
b10000000000000000000000000000011 (
#5000
0'
#6000
1'
b1 #
b1 +
b1 n
#7000
0'
#8000
bx !
bx .
1'
b10 n
#9000
0'
#10000
1'
b11 n
#11000
0'
#12000
1'
b1111111111 #
b1111111111 +
b100 n
#13000
0'
#14000
1'
b101 n
#15000
0'
#16000
1'
b0 #
b0 +
b110 n
#17000
0'
#18000
1'
b10 #
b10 +
b111 n
#19000
0'
#20000
1'
b1 #
b1 +
b1000 n
#21000
0'
#22000
1'
b1111111110 #
b1111111110 +
b1001 n
#23000
0'
#24000
1'
b1010 n
#25000
0'
#26000
1'
b10 #
b10 +
b1011 n
#27000
0'
#28000
1'
b100 #
b100 +
b1100 n
#29000
0'
#30000
1'
b1111111111 #
b1111111111 +
b1101 n
#31000
0'
#32000
1'
b1111111011 #
b1111111011 +
b1110 n
#33000
0'
#34000
1'
b1111111111 #
b1111111111 +
b1111 n
#35000
0'
#36000
1'
b110 #
b110 +
b10000 n
#37000
0'
#38000
1'
b100 #
b100 +
b10001 n
#39000
0'
#40000
1'
b1111111001 #
b1111111001 +
b10010 n
#41000
0'
#42000
1'
b1111111000 #
b1111111000 +
b10011 n
#43000
0'
#44000
1'
b101 #
b101 +
b10100 n
#45000
0'
#46000
1'
b1101 #
b1101 +
b10101 n
#47000
0'
#48000
1'
b1111111111 #
b1111111111 +
b10110 n
#49000
0'
#50000
1'
b1111101110 #
b1111101110 +
b10111 n
#51000
0'
#52000
1'
b1111111010 #
b1111111010 +
b11000 n
#53000
0'
#54000
1'
b10111 #
b10111 +
b11001 n
#55000
0'
#56000
1'
b10011 #
b10011 +
b11010 n
#57000
0'
#58000
1'
b1111100101 #
b1111100101 +
b11011 n
#59000
0'
#60000
1'
b1111010011 #
b1111010011 +
b11100 n
#61000
0'
#62000
1'
b11101 #
b11101 +
b11101 n
#63000
0'
#64000
1'
b10100000 #
b10100000 +
b11110 n
#65000
0'
#66000
1'
b11100010 #
b11100010 +
b11111 n
#67000
0'
#68000
1'
b10100000 #
b10100000 +
b100000 n
#69000
0'
#70000
1'
b11101 #
b11101 +
b100001 n
#71000
0'
#72000
1'
b1111010011 #
b1111010011 +
b100010 n
#73000
0'
#74000
1'
b1111100101 #
b1111100101 +
b100011 n
#75000
0'
#76000
1'
b10011 #
b10011 +
b100100 n
#77000
0'
#78000
1'
b10111 #
b10111 +
b100101 n
#79000
0'
#80000
1'
b1111111010 #
b1111111010 +
b100110 n
#81000
0'
#82000
1'
b1111101110 #
b1111101110 +
b100111 n
#83000
0'
#84000
1'
b1111111111 #
b1111111111 +
b101000 n
#85000
0'
#86000
1'
b1101 #
b1101 +
b101001 n
#87000
0'
#88000
1'
b101 #
b101 +
b101010 n
#89000
0'
#90000
1'
b1111111000 #
b1111111000 +
b101011 n
#91000
0'
#92000
1'
b1111111001 #
b1111111001 +
b101100 n
#93000
0'
#94000
1'
b100 #
b100 +
b101101 n
#95000
0'
#96000
1'
b110 #
b110 +
b101110 n
#97000
0'
#98000
1'
b1111111111 #
b1111111111 +
b101111 n
#99000
0'
#100000
1'
b1111111011 #
b1111111011 +
b110000 n
#101000
0'
#102000
1'
b1111111111 #
b1111111111 +
b110001 n
#103000
0'
#104000
1'
b100 #
b100 +
b110010 n
#105000
0'
#106000
1'
b10 #
b10 +
b110011 n
#107000
0'
#108000
1'
b1111111110 #
b1111111110 +
b110100 n
#109000
0'
#110000
1'
b110101 n
#111000
0'
#112000
1'
b1 #
b1 +
b110110 n
#113000
0'
#114000
1'
b10 #
b10 +
b110111 n
#115000
0'
#116000
1'
b0 #
b0 +
b111000 n
#117000
0'
#118000
1'
b1111111111 #
b1111111111 +
b111001 n
#119000
0'
#120000
1'
b111010 n
#121000
0'
#122000
1'
b1 #
b1 +
b111011 n
#123000
0'
#124000
1'
b111100 n
#125000
0'
#126000
1'
b111101 n
#127000
0'
#128000
1'
b0 #
b0 +
b111110 n
#129000
0'
#130000
b0 -
1'
b0 %
b0 ,
0$
b10000000000000000000000000000100 )
b111111 n
#131000
0'
#132000
b111111111 -
1'
b111111111 %
b111111111 ,
#133000
0'
#134000
b10011010 -
1'
b10011010 %
b10011010 ,
#135000
0'
#136000
b1001100000 -
1'
b1001100000 %
b1001100000 ,
#137000
0'
#138000
b1100000111 -
1'
b1100000111 %
b1100000111 ,
#139000
0'
#140000
b100000110 -
1'
b100000110 %
b100000110 ,
#141000
0'
#142000
b11111001 -
1'
b11111001 %
b11111001 ,
#143000
0'
#144000
b1110010100 -
1'
b1110010100 %
b1110010100 ,
#145000
0'
#146000
b1101100110 -
1'
b1101100110 %
b1101100110 ,
#147000
0'
#148000
b1101 -
1'
b1101 %
b1101 ,
#149000
0'
#150000
b0 -
1'
b0 %
b0 ,
#151000
0'
#152000
b1111110011 -
1'
b1111110011 %
b1111110011 ,
#153000
0'
#154000
b10011010 -
1'
b10011010 %
b10011010 ,
#155000
0'
#156000
b1101100 -
1'
b1101100 %
b1101100 ,
#157000
0'
#158000
b1100000111 -
1'
b1100000111 %
b1100000111 ,
#159000
0'
#160000
b1011111010 -
1'
b1011111010 %
b1011111010 ,
#161000
0'
#162000
b11111001 -
1'
b11111001 %
b11111001 ,
#163000
0'
#164000
b110100000 -
1'
b110100000 %
b110100000 ,
#165000
0'
#166000
b1101100110 -
1'
b1101100110 %
b1101100110 ,
#167000
0'
#168000
b1000000001 -
1'
b1000000001 %
b1000000001 ,
#169000
0'
#170000
b0 -
1'
b0 %
b0 ,
#171000
0'
#172000
b111111111 -
1'
b111111111 %
b111111111 ,
#173000
0'
#174000
b10011010 -
1'
b10011010 %
b10011010 ,
#175000
0'
#176000
b1001100000 -
1'
b1001100000 %
b1001100000 ,
#177000
0'
#178000
b1100000111 -
1'
b1100000111 %
b1100000111 ,
#179000
0'
#180000
b100000110 -
1'
b100000110 %
b100000110 ,
#181000
0'
#182000
b11111001 -
1'
b11111001 %
b11111001 ,
#183000
0'
#184000
b1110010100 -
1'
b1110010100 %
b1110010100 ,
#185000
0'
#186000
b1101100110 -
1'
b1101100110 %
b1101100110 ,
#187000
0'
#188000
b1101 -
1'
b1101 %
b1101 ,
#189000
0'
#190000
b0 -
1'
b0 %
b0 ,
#191000
0'
#192000
b1111110011 -
1'
b1111110011 %
b1111110011 ,
#193000
0'
#194000
b10011010 -
1'
b10011010 %
b10011010 ,
#195000
0'
#196000
b1101100 -
1'
b1101100 %
b1101100 ,
#197000
0'
#198000
b1100000111 -
1'
b1100000111 %
b1100000111 ,
#199000
0'
#200000
b1011111010 -
1'
b1011111010 %
b1011111010 ,
#201000
0'
#202000
b11111001 -
1'
b11111001 %
b11111001 ,
#203000
0'
#204000
b110100000 -
1'
b110100000 %
b110100000 ,
#205000
0'
#206000
b1101100110 -
1'
b1101100110 %
b1101100110 ,
#207000
0'
#208000
b1000000001 -
1'
b1000000001 %
b1000000001 ,
#209000
0'
#210000
b0 -
1'
b0 %
b0 ,
#211000
0'
#212000
b111111111 -
1'
b111111111 %
b111111111 ,
#213000
0'
#214000
b10011010 -
1'
b10011010 %
b10011010 ,
#215000
0'
#216000
b1001100000 -
1'
b1001100000 %
b1001100000 ,
#217000
0'
#218000
b1100000111 -
1'
b1100000111 %
b1100000111 ,
#219000
0'
#220000
b100000110 -
1'
b100000110 %
b100000110 ,
#221000
0'
#222000
b11111001 -
1'
b11111001 %
b11111001 ,
#223000
0'
#224000
b1110010100 -
1'
b1110010100 %
b1110010100 ,
#225000
0'
#226000
b1101100110 -
1'
b1101100110 %
b1101100110 ,
#227000
0'
#228000
b1101 -
1'
b1101 %
b1101 ,
#229000
0'
#230000
b0 -
1'
b0 %
b0 ,
#231000
0'
#232000
b1111110011 -
1'
b1111110011 %
b1111110011 ,
#233000
0'
#234000
b10011010 -
1'
b10011010 %
b10011010 ,
#235000
0'
#236000
b1101100 -
1'
b1101100 %
b1101100 ,
#237000
0'
#238000
b1100000111 -
1'
b1100000111 %
b1100000111 ,
#239000
0'
#240000
b1011111010 -
1'
b1011111010 %
b1011111010 ,
#241000
0'
#242000
b11111001 -
1'
b11111001 %
b11111001 ,
#243000
0'
#244000
b110100000 -
1'
b110100000 %
b110100000 ,
#245000
0'
#246000
b1101100110 -
1'
b1101100110 %
b1101100110 ,
#247000
0'
#248000
b1000000001 -
1'
b1000000001 %
b1000000001 ,
#249000
0'
#250000
b0 -
1'
b0 %
b0 ,
#251000
0'
#252000
b111111111 -
1'
b111111111 %
b111111111 ,
#253000
0'
#254000
b10011010 -
1'
b10011010 %
b10011010 ,
#255000
0'
#256000
b1001100000 -
1'
b1001100000 %
b1001100000 ,
#257000
0'
#258000
b11111010 !
b11111010 .
b1100000111 -
1'
b1100000111 %
b1100000111 ,
#259000
0'
#260000
b10011001 !
b10011001 .
b100000110 -
1'
b100000110 %
b100000110 ,
#261000
0'
#262000
b1101100100 !
b1101100100 .
b11111001 -
1'
b11111001 %
b11111001 ,
#263000
0'
#264000
b1100000111 !
b1100000111 .
b1110010100 -
1'
b1110010100 %
b1110010100 ,
#265000
0'
#266000
b10 !
b10 .
b1101100110 -
1'
b1101100110 %
b1101100110 ,
#267000
0'
#268000
b11111000 !
b11111000 .
b1101 -
1'
b1101 %
b1101 ,
#269000
0'
#270000
b10010111 !
b10010111 .
b0 -
1'
b0 %
b0 ,
#271000
0'
#272000
b1101100110 !
b1101100110 .
b1111110011 -
1'
b1111110011 %
b1111110011 ,
#273000
0'
#274000
b1100001001 !
b1100001001 .
b10011010 -
1'
b10011010 %
b10011010 ,
#275000
0'
#276000
b0 !
b0 .
b1101100 -
1'
b1101100 %
b1101100 ,
#277000
0'
#278000
b11110110 !
b11110110 .
b1100000111 -
1'
b1100000111 %
b1100000111 ,
#279000
0'
#280000
b10011001 !
b10011001 .
b1011111010 -
1'
b1011111010 %
b1011111010 ,
#281000
0'
#282000
b1101101000 !
b1101101000 .
b11111001 -
1'
b11111001 %
b11111001 ,
#283000
0'
#284000
b1100000111 !
b1100000111 .
b110100000 -
1'
b110100000 %
b110100000 ,
#285000
0'
#286000
b1111111101 !
b1111111101 .
b1101100110 -
1'
b1101100110 %
b1101100110 ,
#287000
0'
#288000
b11111000 !
b11111000 .
b1000000001 -
1'
b1000000001 %
b1000000001 ,
#289000
0'
#290000
b10011011 !
b10011011 .
b0 -
1'
b0 %
b0 ,
#291000
0'
#292000
b1101100110 !
b1101100110 .
b111111111 -
1'
b111111111 %
b111111111 ,
#293000
0'
#294000
b1100000101 !
b1100000101 .
b10011010 -
1'
b10011010 %
b10011010 ,
#295000
0'
#296000
b0 !
b0 .
b1001100000 -
1'
b1001100000 %
b1001100000 ,
#297000
0'
#298000
b11111010 !
b11111010 .
b1100000111 -
1'
b1100000111 %
b1100000111 ,
#299000
0'
#300000
b10011001 !
b10011001 .
b100000110 -
1'
b100000110 %
b100000110 ,
#301000
0'
#302000
b1101100100 !
b1101100100 .
b11111001 -
1'
b11111001 %
b11111001 ,
#303000
0'
#304000
b1100000111 !
b1100000111 .
b1110010100 -
1'
b1110010100 %
b1110010100 ,
#305000
0'
#306000
b10 !
b10 .
b1101100110 -
1'
b1101100110 %
b1101100110 ,
#307000
0'
#308000
b11111000 !
b11111000 .
b1101 -
1'
b1101 %
b1101 ,
#309000
0'
#310000
b10010111 !
b10010111 .
b0 -
1'
b0 %
b0 ,
#311000
0'
#312000
b1101100110 !
b1101100110 .
b1111110011 -
1'
b1111110011 %
b1111110011 ,
#313000
0'
#314000
b1100001001 !
b1100001001 .
b10011010 -
1'
b10011010 %
b10011010 ,
#315000
0'
#316000
b0 !
b0 .
b1101100 -
1'
b1101100 %
b1101100 ,
#317000
0'
#318000
b11110110 !
b11110110 .
b1100000111 -
1'
b1100000111 %
b1100000111 ,
#319000
0'
#320000
b10011001 !
b10011001 .
b1011111010 -
1'
b1011111010 %
b1011111010 ,
#321000
0'
#322000
b1101101000 !
b1101101000 .
b11111001 -
1'
b11111001 %
b11111001 ,
#323000
0'
#324000
b1100000111 !
b1100000111 .
b110100000 -
1'
b110100000 %
b110100000 ,
#325000
0'
#326000
b1111111101 !
b1111111101 .
b1101100110 -
1'
b1101100110 %
b1101100110 ,
#327000
0'
#328000
b11111000 !
b11111000 .
b1000000001 -
1'
b1000000001 %
b1000000001 ,
#329000
0'
#330000
b10011011 !
b10011011 .
b0 -
1'
b0 %
b0 ,
#331000
0'
#332000
b1101100110 !
b1101100110 .
b111111111 -
1'
b111111111 %
b111111111 ,
#333000
0'
#334000
b1100000101 !
b1100000101 .
b10011010 -
1'
b10011010 %
b10011010 ,
#335000
0'
#336000
b0 !
b0 .
b1001100000 -
1'
b1001100000 %
b1001100000 ,
#337000
0'
#338000
b11111010 !
b11111010 .
b1100000111 -
1'
b1100000111 %
b1100000111 ,
#339000
0'
#340000
b10011001 !
b10011001 .
b100000110 -
1'
b100000110 %
b100000110 ,
#341000
0'
#342000
b1101100100 !
b1101100100 .
b11111001 -
1'
b11111001 %
b11111001 ,
#343000
0'
#344000
b1100000111 !
b1100000111 .
b1110010100 -
1'
b1110010100 %
b1110010100 ,
#345000
0'
#346000
b10 !
b10 .
b1101100110 -
1'
b1101100110 %
b1101100110 ,
#347000
0'
#348000
b11111000 !
b11111000 .
b1101 -
1'
b1101 %
b1101 ,
#349000
0'
#350000
b10010111 !
b10010111 .
b0 -
1'
b0 %
b0 ,
#351000
0'
#352000
b1101100110 !
b1101100110 .
b1111110011 -
1'
b1111110011 %
b1111110011 ,
#353000
0'
#354000
b1100001001 !
b1100001001 .
b10011010 -
1'
b10011010 %
b10011010 ,
#355000
0'
#356000
b0 !
b0 .
b1101100 -
1'
b1101100 %
b1101100 ,
#357000
0'
#358000
b11110110 !
b11110110 .
b1100000111 -
1'
b1100000111 %
b1100000111 ,
#359000
0'
#360000
b10011001 !
b10011001 .
b1011111010 -
1'
b1011111010 %
b1011111010 ,
#361000
0'
#362000
b1101101000 !
b1101101000 .
b11111001 -
1'
b11111001 %
b11111001 ,
#363000
0'
#364000
b1100000111 !
b1100000111 .
b110100000 -
1'
b110100000 %
b110100000 ,
#365000
0'
#366000
b1111111101 !
b1111111101 .
b1101100110 -
1'
b1101100110 %
b1101100110 ,
#367000
0'
#368000
b11111000 !
b11111000 .
b1000000001 -
1'
b1000000001 %
b1000000001 ,
#369000
0'
#370000
b10011011 !
b10011011 .
b0 -
1'
b0 %
b0 ,
#371000
0'
#372000
b1101100110 !
b1101100110 .
b111111111 -
1'
b111111111 %
b111111111 ,
#373000
0'
#374000
b1100000101 !
b1100000101 .
b10011010 -
1'
b10011010 %
b10011010 ,
#375000
0'
#376000
b0 !
b0 .
b1001100000 -
1'
b1001100000 %
b1001100000 ,
#377000
0'
#378000
b11111010 !
b11111010 .
b1100000111 -
1'
b1100000111 %
b1100000111 ,
#379000
0'
#380000
b10011001 !
b10011001 .
b100000110 -
1'
b100000110 %
b100000110 ,
#381000
0'
#382000
b1101100100 !
b1101100100 .
b11111001 -
1'
b11111001 %
b11111001 ,
#383000
0'
#384000
b1100000111 !
b1100000111 .
b1110010100 -
1'
b1110010100 %
b1110010100 ,
#385000
0'
#386000
b10 !
b10 .
b1101100110 -
1'
b1101100110 %
b1101100110 ,
#387000
0'
#388000
b11111000 !
b11111000 .
b1101 -
1'
b1101 %
b1101 ,
#389000
0'
#390000
b10010111 !
b10010111 .
b0 -
1'
b0 %
b0 ,
#391000
0'
#392000
b1101100110 !
b1101100110 .
b1111110011 -
1'
b1111110011 %
b1111110011 ,
#393000
0'
#394000
b1100001001 !
b1100001001 .
b10011010 -
1'
b10011010 %
b10011010 ,
#395000
0'
#396000
b0 !
b0 .
b1101100 -
1'
b1101100 %
b1101100 ,
#397000
0'
#398000
b11110110 !
b11110110 .
b1100000111 -
1'
b1100000111 %
b1100000111 ,
#399000
0'
#400000
b10011001 !
b10011001 .
b1011111010 -
1'
b1011111010 %
b1011111010 ,
#401000
0'
#402000
b1101101000 !
b1101101000 .
b11111001 -
1'
b11111001 %
b11111001 ,
#403000
0'
#404000
b1100000111 !
b1100000111 .
b110100000 -
1'
b110100000 %
b110100000 ,
#405000
0'
#406000
b1111111101 !
b1111111101 .
b1101100110 -
1'
b1101100110 %
b1101100110 ,
#407000
0'
#408000
b11111000 !
b11111000 .
b1000000001 -
1'
b1000000001 %
b1000000001 ,
#409000
0'
#410000
b10011011 !
b10011011 .
b0 -
1'
b0 %
b0 ,
#411000
0'
#412000
b1101100110 !
b1101100110 .
b111111111 -
1'
b111111111 %
b111111111 ,
#413000
0'
#414000
b1100000101 !
b1100000101 .
b10011010 -
1'
b10011010 %
b10011010 ,
#415000
0'
#416000
b0 !
b0 .
b1001100000 -
1'
b1001100000 %
b1001100000 ,
#417000
0'
#418000
b11111010 !
b11111010 .
b1100000111 -
1'
b1100000111 %
b1100000111 ,
#419000
0'
#420000
b10011001 !
b10011001 .
b100000110 -
1'
b100000110 %
b100000110 ,
#421000
0'
#422000
b1101100100 !
b1101100100 .
b11111001 -
1'
b11111001 %
b11111001 ,
#423000
0'
#424000
b1100000111 !
b1100000111 .
b1110010100 -
1'
b1110010100 %
b1110010100 ,
#425000
0'
#426000
b10 !
b10 .
b1101100110 -
1'
b1101100110 %
b1101100110 ,
#427000
0'
#428000
b11111000 !
b11111000 .
b1101 -
1'
b1101 %
b1101 ,
#429000
0'
#430000
b10010111 !
b10010111 .
b0 -
1'
b0 %
b0 ,
#431000
0'
#432000
b1101100110 !
b1101100110 .
b1111110011 -
1'
b1111110011 %
b1111110011 ,
#433000
0'
#434000
b1100001001 !
b1100001001 .
b10011010 -
1'
b10011010 %
b10011010 ,
#435000
0'
#436000
b0 !
b0 .
b1101100 -
1'
b1101100 %
b1101100 ,
#437000
0'
#438000
b11110110 !
b11110110 .
b1100000111 -
1'
b1100000111 %
b1100000111 ,
#439000
0'
#440000
b10011001 !
b10011001 .
b1011111010 -
1'
b1011111010 %
b1011111010 ,
#441000
0'
#442000
b1101101000 !
b1101101000 .
b11111001 -
1'
b11111001 %
b11111001 ,
#443000
0'
#444000
b1100000111 !
b1100000111 .
b110100000 -
1'
b110100000 %
b110100000 ,
#445000
0'
#446000
b1111111101 !
b1111111101 .
b1101100110 -
1'
b1101100110 %
b1101100110 ,
#447000
0'
#448000
b11111000 !
b11111000 .
b1000000001 -
1'
b1000000001 %
b1000000001 ,
#449000
0'
#450000
b0 *
